mcount/__init__.py
mcount/main.py
mtcount-0.1.1.dist-info/METADATA
mtcount-0.1.1.dist-info/WHEEL
mtcount-0.1.1.dist-info/entry_points.txt
mtcount-0.1.1.dist-info/top_level.txt
mtcount-0.1.1.dist-info/RECORD
