Metadata-Version: 2.1
Name: mtcount
Version: 0.1.1
Summary: A lightweight tool for counting metastatic cells in cancerous tissue samples
Home-page: https://github.com/abd-ur/MTC_Count
Author: Abdur Rahman Ansari
Author-email: theabdur10@gmail.com
Classifier: Programming Language :: Python :: 3
Classifier: License :: OSI Approved :: MIT License
Classifier: Operating System :: OS Independent
Requires-Python: >=3.6
Requires-Dist: opencv-python
Requires-Dist: numpy
Requires-Dist: scipy
